{
	"configurations" : 
	[
		{
			"directories" : 
			[
				{
					"build" : ".",
					"childIndexes" : 
					[
						1
					],
					"jsonFile" : "directory-.-Debug-d0094a50bb2071803777.json",
					"minimumCMakeVersion" : 
					{
						"string" : "3.15"
					},
					"projectIndex" : 0,
					"source" : ".",
					"targetIndexes" : 
					[
						1,
						2
					]
				},
				{
					"build" : "test",
					"jsonFile" : "directory-test-Debug-f18be1977b403cfd1a50.json",
					"minimumCMakeVersion" : 
					{
						"string" : "3.15"
					},
					"parentIndex" : 0,
					"projectIndex" : 0,
					"source" : "test",
					"targetIndexes" : 
					[
						0
					]
				}
			],
			"name" : "Debug",
			"projects" : 
			[
				{
					"directoryIndexes" : 
					[
						0,
						1
					],
					"name" : "RedShiftWeaponizer",
					"targetIndexes" : 
					[
						0,
						1,
						2
					]
				}
			],
			"targets" : 
			[
				{
					"directoryIndex" : 1,
					"id" : "RedShiftTests::@36f028580bb02cc8272a",
					"jsonFile" : "target-RedShiftTests-Debug-41dbe1123e195ba61edd.json",
					"name" : "RedShiftTests",
					"projectIndex" : 0
				},
				{
					"directoryIndex" : 0,
					"id" : "RedShiftWeaponizer::@6890427a1f51a3e7e1df",
					"jsonFile" : "target-RedShiftWeaponizer-Debug-863fb951421ad912d5c6.json",
					"name" : "RedShiftWeaponizer",
					"projectIndex" : 0
				},
				{
					"directoryIndex" : 0,
					"id" : "WeaponizerCore::@6890427a1f51a3e7e1df",
					"jsonFile" : "target-WeaponizerCore-Debug-044f2af358beb3e34dd2.json",
					"name" : "WeaponizerCore",
					"projectIndex" : 0
				}
			]
		}
	],
	"kind" : "codemodel",
	"paths" : 
	{
		"build" : "C:/Users/brand/OneDrive/Desktop/Programs/CIS-25/Red Shift Weaponizer/out/build/x64-Debug",
		"source" : "C:/Users/brand/OneDrive/Desktop/Programs/CIS-25/Red Shift Weaponizer"
	},
	"version" : 
	{
		"major" : 2,
		"minor" : 8
	}
}
